{
    "platform": "PC",
    "sounds": [
        {
            "hash": "CHAR/MOON_V/CANTGO1",
            "sample_index": 0,
            "flags": 31
        },
        {
            "hash": "CHAR/MOON_V/CANTGO2",
            "sample_index": 1,
            "flags": 31
        },
        {
            "hash": "CHAR/MOON_V/CMDATTACKANY/***RANDOM***/0",
            "sample_index": 2,
            "flags": 31
        },
        {
            "hash": "CHAR/MOON_V/CMDATTACKANY/***RANDOM***/1",
            "sample_index": 3,
            "flags": 31
        },
        {
            "hash": "CHAR/MOON_V/CMDATTACKANY/***RANDOM***/2",
            "sample_index": 4,
            "flags": 31
        },
        {
            "hash": "CHAR/MOON_V/CMDATTACKTARGET/***RANDOM***/0",
            "sample_index": 5,
            "flags": 31
        },
        {
            "hash": "CHAR/MOON_V/CMDATTACKTARGET/***RANDOM***/1",
            "sample_index": 6,
            "flags": 31
        },
        {
            "hash": "CHAR/MOON_V/CMDATTACKTARGET/***RANDOM***/2",
            "sample_index": 7,
            "flags": 31
        },
        {
            "hash": "CHAR/MOON_V/CMDFOLLOW/***RANDOM***/0",
            "sample_index": 8,
            "flags": 31
        },
        {
            "hash": "CHAR/MOON_V/CMDFOLLOW/***RANDOM***/1",
            "sample_index": 9,
            "flags": 31
        },
        {
            "hash": "CHAR/MOON_V/CMDFOLLOW/***RANDOM***/2",
            "sample_index": 10,
            "flags": 31
        },
        {
            "hash": "CHAR/MOON_V/EPITAPH/***RANDOM***/0",
            "sample_index": 11,
            "flags": 31
        },
        {
            "hash": "CHAR/MOON_V/EPITAPH/***RANDOM***/1",
            "sample_index": 12,
            "flags": 31
        },
        {
            "hash": "CHAR/MOON_V/EPITAPH/***RANDOM***/2",
            "sample_index": 13,
            "flags": 31
        },
        {
            "hash": "CHAR/MOON_V/EPITAPH2",
            "sample_index": 12,
            "flags": 31
        },
        {
            "hash": "CHAR/MOON_V/EPITAPH3",
            "sample_index": 13,
            "flags": 31
        },
        {
            "hash": "CHAR/MOON_V/ISEEYOU",
            "sample_index": 14,
            "flags": 31
        },
        {
            "hash": "CHAR/MOON_V/ISEEYOU2",
            "sample_index": 15,
            "flags": 31
        },
        {
            "hash": "CHAR/MOON_V/ISEEYOU3",
            "sample_index": 16,
            "flags": 31
        },
        {
            "hash": "CHAR/MOON_V/ISEEYOU4",
            "sample_index": 17,
            "flags": 31
        },
        {
            "hash": "CHAR/MOON_V/ISEEYOU5",
            "sample_index": 18,
            "flags": 31
        },
        {
            "hash": "CHAR/MOON_V/ISEEYOU6",
            "sample_index": 19,
            "flags": 31
        },
        {
            "hash": "CHAR/MOON_V/ISEEYOU7",
            "sample_index": 20,
            "flags": 31
        },
        {
            "hash": "CHAR/MOON_V/ISEEYOU8",
            "sample_index": 21,
            "flags": 31
        },
        {
            "hash": "CHAR/MOON_V/LEVELUP1_C",
            "sample_index": 22,
            "flags": 31
        },
        {
            "hash": "CHAR/MOON_V/LEVELUP2",
            "sample_index": 23,
            "flags": 31
        },
        {
            "hash": "CHAR/MOON_V/LEVELUP3",
            "sample_index": 24,
            "flags": 31
        },
        {
            "hash": "CHAR/MOON_V/NOPOWER/***RANDOM***/0",
            "sample_index": 25,
            "flags": 31
        },
        {
            "hash": "CHAR/MOON_V/NOPOWER/***RANDOM***/1",
            "sample_index": 26,
            "flags": 31
        },
        {
            "hash": "CHAR/MOON_V/NOWORK/***RANDOM***/0",
            "sample_index": 27,
            "flags": 31
        },
        {
            "hash": "CHAR/MOON_V/NOWORK/***RANDOM***/1",
            "sample_index": 28,
            "flags": 31
        },
        {
            "hash": "CHAR/MOON_V/NOWORK3",
            "sample_index": 29,
            "flags": 31
        },
        {
            "hash": "CHAR/MOON_V/RESPAFFIRM/***RANDOM***/0",
            "sample_index": 30,
            "flags": 31
        },
        {
            "hash": "CHAR/MOON_V/RESPAFFIRM/***RANDOM***/1",
            "sample_index": 31,
            "flags": 31
        },
        {
            "hash": "CHAR/MOON_V/RESPAFFIRM/***RANDOM***/2",
            "sample_index": 32,
            "flags": 31
        },
        {
            "hash": "CHAR/MOON_V/STRUGGLE",
            "sample_index": 33,
            "flags": 31
        },
        {
            "hash": "CHAR/MOON_V/TAUNTKD/***RANDOM***/0",
            "sample_index": 34,
            "flags": 31
        },
        {
            "hash": "CHAR/MOON_V/TAUNTKD/***RANDOM***/1",
            "sample_index": 35,
            "flags": 31
        },
        {
            "hash": "CHAR/MOON_V/TAUNTKD/***RANDOM***/2",
            "sample_index": 36,
            "flags": 31
        },
        {
            "hash": "CHAR/MOON_V/TAUNTKD/***RANDOM***/3",
            "sample_index": 37,
            "flags": 31
        },
        {
            "hash": "CHAR/MOON_V/THROWTAUNT/***RANDOM***/0",
            "sample_index": 38,
            "flags": 31
        },
        {
            "hash": "CHAR/MOON_V/THROWTAUNT/***RANDOM***/1",
            "sample_index": 39,
            "flags": 31
        },
        {
            "hash": "CHAR/MOON_V/THROWTAUNT/***RANDOM***/2",
            "sample_index": 40,
            "flags": 31
        },
        {
            "hash": "CHAR/MOON_V/TOOHEAVY/***RANDOM***/0",
            "sample_index": 41,
            "flags": 31
        },
        {
            "hash": "CHAR/MOON_V/TOOHEAVY/***RANDOM***/1",
            "sample_index": 42,
            "flags": 31
        },
        {
            "hash": "CHAR/MOON_V/VICTORY/***RANDOM***/0",
            "sample_index": 43,
            "flags": 31
        },
        {
            "hash": "CHAR/MOON_V/VICTORY/***RANDOM***/1",
            "sample_index": 44,
            "flags": 31
        },
        {
            "hash": "CHAR/MOON_V/VICTORY/***RANDOM***/2",
            "sample_index": 45,
            "flags": 31
        },
        {
            "hash": "CHAR/MOON_V/VICTORY/***RANDOM***/3",
            "sample_index": 46,
            "flags": 31
        },
        {
            "hash": "CHAR/MOON_V/VICTORY/***RANDOM***/4",
            "sample_index": 47,
            "flags": 31
        },
        {
            "hash": "CHAR/MOON_V/VICTORY/***RANDOM***/5",
            "sample_index": 48,
            "flags": 31
        },
        {
            "hash": "CHAR/MOON_V/XTREME/***RANDOM***/0",
            "sample_index": 49,
            "flags": 31
        },
        {
            "hash": "CHAR/MOON_V/XTREME/***RANDOM***/1",
            "sample_index": 50,
            "flags": 31
        }
    ],
    "samples": [
        {
            "file": "moon_v\\CANTGO1.wav",
            "format": 106,
            "sample_rate": 44100
        },
        {
            "file": "moon_v\\CANTGO2.wav",
            "format": 106,
            "sample_rate": 44100
        },
        {
            "file": "moon_v\\CMDATTACKANY1.wav",
            "format": 106,
            "sample_rate": 44100
        },
        {
            "file": "moon_v\\CMDATTACKANY2.wav",
            "format": 106,
            "sample_rate": 44100
        },
        {
            "file": "moon_v\\CMDATTACKANY3.wav",
            "format": 106,
            "sample_rate": 44100
        },
        {
            "file": "moon_v\\CMDATTACKTARGET1.wav",
            "format": 106,
            "sample_rate": 44100
        },
        {
            "file": "moon_v\\CMDATTACKTARGET2.wav",
            "format": 106,
            "sample_rate": 44100
        },
        {
            "file": "moon_v\\CMDATTACKTARGET3.wav",
            "format": 106,
            "sample_rate": 44100
        },
        {
            "file": "moon_v\\CMDFOLLOW1.wav",
            "format": 106,
            "sample_rate": 44100
        },
        {
            "file": "moon_v\\CMDFOLLOW2.wav",
            "format": 106,
            "sample_rate": 44100
        },
        {
            "file": "moon_v\\CMDFOLLOW3.wav",
            "format": 106,
            "sample_rate": 44100
        },
        {
            "file": "moon_v\\EPITAPH1.wav",
            "format": 106,
            "sample_rate": 44100
        },
        {
            "file": "moon_v\\EPITAPH2.wav",
            "format": 106,
            "sample_rate": 44100
        },
        {
            "file": "moon_v\\EPITAPH3.wav",
            "format": 106,
            "sample_rate": 44100
        },
        {
            "file": "moon_v\\ISEEYOU.wav",
            "format": 106,
            "sample_rate": 44100
        },
        {
            "file": "moon_v\\ISEEYOU2.wav",
            "format": 106,
            "sample_rate": 44100
        },
        {
            "file": "moon_v\\ISEEYOU3.wav",
            "format": 106,
            "sample_rate": 44100
        },
        {
            "file": "moon_v\\ISEEYOU4.wav",
            "format": 106,
            "sample_rate": 44100
        },
        {
            "file": "moon_v\\ISEEYOU5.wav",
            "format": 106,
            "sample_rate": 44100
        },
        {
            "file": "moon_v\\ISEEYOU6.wav",
            "format": 106,
            "sample_rate": 44100
        },
        {
            "file": "moon_v\\ISEEYOU7.wav",
            "format": 106,
            "sample_rate": 44100
        },
        {
            "file": "moon_v\\ISEEYOU8.wav",
            "format": 106,
            "sample_rate": 44100
        },
        {
            "file": "moon_v\\LEVELUP1_C.wav",
            "format": 106,
            "sample_rate": 44100
        },
        {
            "file": "moon_v\\LEVELUP2.wav",
            "format": 106,
            "sample_rate": 44100
        },
        {
            "file": "moon_v\\LEVELUP3.wav",
            "format": 106,
            "sample_rate": 44100
        },
        {
            "file": "moon_v\\NOPOWER1.wav",
            "format": 106,
            "sample_rate": 44100
        },
        {
            "file": "moon_v\\NOPOWER2.wav",
            "format": 106,
            "sample_rate": 44100
        },
        {
            "file": "moon_v\\NOWORK2.wav",
            "format": 106,
            "sample_rate": 44100
        },
        {
            "file": "moon_v\\NOWORK1.wav",
            "format": 106,
            "sample_rate": 44100
        },
        {
            "file": "moon_v\\NOWORK3.wav",
            "format": 106,
            "sample_rate": 44100
        },
        {
            "file": "moon_v\\RESPAFFIRM1.wav",
            "format": 106,
            "sample_rate": 44100
        },
        {
            "file": "moon_v\\RESPAFFIRM3.wav",
            "format": 106,
            "sample_rate": 44100
        },
        {
            "file": "moon_v\\RESPAFFIRM2.wav",
            "format": 106,
            "sample_rate": 44100
        },
        {
            "file": "moon_v\\STRUGGLE2.wav",
            "format": 106,
            "sample_rate": 44100
        },
        {
            "file": "moon_v\\TAUNTKD1.wav",
            "format": 106,
            "sample_rate": 44100
        },
        {
            "file": "moon_v\\TAUNTKD4.wav",
            "format": 106,
            "sample_rate": 44100
        },
        {
            "file": "moon_v\\TAUNTKD2.wav",
            "format": 106,
            "sample_rate": 44100
        },
        {
            "file": "moon_v\\TAUNTKD3.wav",
            "format": 106,
            "sample_rate": 44100
        },
        {
            "file": "moon_v\\THROWTAUNT.wav",
            "format": 106,
            "sample_rate": 44100
        },
        {
            "file": "moon_v\\THROWTAUNT3.wav",
            "format": 106,
            "sample_rate": 44100
        },
        {
            "file": "moon_v\\THROWTAUNT2.wav",
            "format": 106,
            "sample_rate": 44100
        },
        {
            "file": "moon_v\\TOOHEAVY1.wav",
            "format": 106,
            "sample_rate": 44100
        },
        {
            "file": "moon_v\\TOOHEAVY2.wav",
            "format": 106,
            "sample_rate": 44100
        },
        {
            "file": "moon_v\\VICTORY1.wav",
            "format": 106,
            "sample_rate": 44100
        },
        {
            "file": "moon_v\\VICTORY2.wav",
            "format": 106,
            "sample_rate": 44100
        },
        {
            "file": "moon_v\\VICTORY3.wav",
            "format": 106,
            "sample_rate": 44100
        },
        {
            "file": "moon_v\\VICTORY4.wav",
            "format": 106,
            "sample_rate": 44100
        },
        {
            "file": "moon_v\\VICTORY5.wav",
            "format": 106,
            "sample_rate": 44100
        },
        {
            "file": "moon_v\\VICTORY6.wav",
            "format": 106,
            "sample_rate": 44100
        },
        {
            "file": "moon_v\\XTREME_C.wav",
            "format": 106,
            "sample_rate": 44100
        },
        {
            "file": "moon_v\\XTREME2_A.wav",
            "format": 106,
            "sample_rate": 44100
        }
    ]
}