{
    "platform": "PC",
    "sounds": [
        {
            "hash": "CHAR/SUN_M/DEATH",
            "sample_index": 0,
            "flags": 255
        },
        {
            "hash": "CHAR/SUN_M/FLYBEGIN",
            "sample_index": 1,
            "flags": 31
        },
        {
            "hash": "CHAR/SUN_M/FLYEND",
            "sample_index": 2,
            "flags": 31
        },
        {
            "hash": "CHAR/SUN_M/JUMP/***RANDOM***/0",
            "sample_index": 3,
            "flags": 31
        },
        {
            "hash": "CHAR/SUN_M/JUMP/***RANDOM***/1",
            "sample_index": 4,
            "flags": 31
        },
        {
            "hash": "CHAR/SUN_M/LAND",
            "sample_index": 5,
            "flags": 31
        },
        {
            "hash": "CHAR/SUN_M/P1_CHARGE",
            "sample_index": 6,
            "flags": 50
        },
        {
            "hash": "CHAR/SUN_M/P1_POWER",
            "sample_index": 7,
            "flags": 50
        },
        {
            "hash": "CHAR/SUN_M/P2_CHARGE",
            "sample_index": 8,
            "flags": 50
        },
        {
            "hash": "CHAR/SUN_M/P3_CHARGE",
            "sample_index": 9,
            "flags": 50
        },
        {
            "hash": "CHAR/SUN_M/P4_IMPACT",
            "sample_index": 10,
            "flags": 12
        },
        {
            "hash": "CHAR/SUN_M/P5_IMPACT",
            "sample_index": 11,
            "flags": 12
        },
        {
            "hash": "CHAR/SUN_M/P5_LOOP",
            "sample_index": 12,
            "flags": 50
        },
        {
            "hash": "CHAR/SUN_M/P6_CHARGE",
            "sample_index": 13,
            "flags": 50
        },
        {
            "hash": "CHAR/SUN_M/P8_CHARGE",
            "sample_index": 14,
            "flags": 50
        },
        {
            "hash": "CHAR/SUN_M/P9_CHARGE",
            "sample_index": 15,
            "flags": 50
        },
        {
            "hash": "CHAR/SUN_M/PAIN/***RANDOM***/0",
            "sample_index": 16,
            "flags": 31
        },
        {
            "hash": "CHAR/SUN_M/PAIN/***RANDOM***/1",
            "sample_index": 17,
            "flags": 31
        },
        {
            "hash": "CHAR/SUN_M/PAIN/***RANDOM***/2",
            "sample_index": 18,
            "flags": 31
        },
        {
            "hash": "CHAR/SUN_M/PICKUP",
            "sample_index": 19,
            "flags": 31
        },
        {
            "hash": "CHAR/SUN_M/THROW",
            "sample_index": 20,
            "flags": 31
        }
    ],
    "samples": [
        {
            "file": "sun_m\\death.wav",
            "format": 106,
            "sample_rate": 22050
        },
        {
            "file": "sun_m\\flybegin.wav",
            "format": 106,
            "sample_rate": 22050
        },
        {
            "file": "sun_m\\flyend.wav",
            "format": 106,
            "sample_rate": 22050
        },
        {
            "file": "sun_m\\jump.wav",
            "format": 106,
            "sample_rate": 22050
        },
        {
            "file": "sun_m\\jump2.wav",
            "format": 106,
            "sample_rate": 22050
        },
        {
            "file": "sun_m\\land.wav",
            "format": 106,
            "sample_rate": 22050
        },
        {
            "file": "sun_m\\p1_charge.wav",
            "format": 106,
            "sample_rate": 22050
        },
        {
            "file": "sun_m\\p1_power.wav",
            "format": 106,
            "sample_rate": 22050
        },
        {
            "file": "sun_m\\p2_charge.wav",
            "format": 106,
            "sample_rate": 22050,
            "flags": 1
        },
        {
            "file": "sun_m\\p3_charge.wav",
            "format": 106,
            "sample_rate": 22050
        },
        {
            "file": "sun_m\\p4_impact.wav",
            "format": 106,
            "sample_rate": 22050
        },
        {
            "file": "sun_m\\p5_impact.wav",
            "format": 106,
            "sample_rate": 22050
        },
        {
            "file": "sun_m\\p5_loop.wav",
            "format": 106,
            "sample_rate": 22050
        },
        {
            "file": "sun_m\\p6_charge.wav",
            "format": 106,
            "sample_rate": 22050
        },
        {
            "file": "sun_m\\p8_charge.wav",
            "format": 106,
            "sample_rate": 22050
        },
        {
            "file": "sun_m\\p9_charge.wav",
            "format": 106,
            "sample_rate": 22050
        },
        {
            "file": "sun_m\\pain.wav",
            "format": 106,
            "sample_rate": 22050
        },
        {
            "file": "sun_m\\pain3.wav",
            "format": 106,
            "sample_rate": 22050
        },
        {
            "file": "sun_m\\pain2.wav",
            "format": 106,
            "sample_rate": 22050
        },
        {
            "file": "sun_m\\pickup.wav",
            "format": 106,
            "sample_rate": 22050
        },
        {
            "file": "sun_m\\throw.wav",
            "format": 106,
            "sample_rate": 22050
        }
    ]
}